__init__.py
geoapi_pandas.py
geoapi_pandas-0.0.5.dist-info/licenses/LICENSE
geoapi_pandas-0.0.5.dist-info/METADATA
geoapi_pandas-0.0.5.dist-info/WHEEL
geoapi_pandas-0.0.5.dist-info/top_level.txt
geoapi_pandas-0.0.5.dist-info/RECORD
