Metadata-Version: 2.4
Name: geoapi-pandas
Version: 0.0.5
Summary: A small geoapi package
Author-email: tda <the.data.analytic@gmail.com>
License-Expression: MIT
Project-URL: Homepage, https://github.com/pypa/sampleproject
Project-URL: Issues, https://github.com/pypa/sampleproject/issues
Classifier: Programming Language :: Python :: 3
Classifier: Operating System :: OS Independent
Requires-Python: >=3.12
License-File: LICENSE
Dynamic: license-file
